<?xml version='1.0' encoding='utf-8'?>
<annotation>
	<folder>Images</folder>
	<filename>208.jpg</filename>
	<path>208.jpg</path>
	<source>
		<database>Unknown</database>
	</source>
	<size>
		<width>5096</width>
		<height>3296</height>
		<depth>1</depth>
	</size>
	<segmented>0</segmented>
	<object>
		<name>208_Copete_power of attorney</name>
		<pose>Unspecified</pose>
		<truncated>0</truncated>
		<difficult>0</difficult>
		<bndbox>
			<xmin>2446</xmin>
			<ymin>259</ymin>
			<xmax>2949</xmax>
			<ymax>656</ymax>
		</bndbox>
	</object>
	<object>
		<name>208_Notiricatio_name and place of residence of parties</name>
		<pose>Unspecified</pose>
		<truncated>0</truncated>
		<difficult>0</difficult>
		<bndbox>
			<xmin>2916</xmin>
			<ymin>143</ymin>
			<xmax>4709</xmax>
			<ymax>484</ymax>
		</bndbox>
	</object>
	<object>
		<name>208_Dispositio_names of parties</name>
		<pose>Unspecified</pose>
		<truncated>0</truncated>
		<difficult>0</difficult>
		<bndbox>
			<xmin>2961</xmin>
			<ymin>999</ymin>
			<xmax>4667</xmax>
			<ymax>1684</ymax>
		</bndbox>
	</object>
	<object>
		<name>208_Scope of deed</name>
		<pose>Unspecified</pose>
		<truncated>0</truncated>
		<difficult>0</difficult>
		<bndbox>
			<xmin>2962</xmin>
			<ymin>495</ymin>
			<xmax>4676</xmax>
			<ymax>993</ymax>
		</bndbox>
	</object>
	<object>
		<name>208_Scope of deed</name>
		<pose>Unspecified</pose>
		<truncated>0</truncated>
		<difficult>0</difficult>
		<bndbox>
			<xmin>2871</xmin>
			<ymin>1698</ymin>
			<xmax>4691</xmax>
			<ymax>2091</ymax>
		</bndbox>
	</object>
	<object>
		<name>208_Scope of deed</name>
		<pose>Unspecified</pose>
		<truncated>0</truncated>
		<difficult>0</difficult>
		<bndbox>
			<xmin>2909</xmin>
			<ymin>2103</ymin>
			<xmax>4729</xmax>
			<ymax>2496</ymax>
		</bndbox>
	</object>
	<object>
		<name>208_Scope of deed</name>
		<pose>Unspecified</pose>
		<truncated>0</truncated>
		<difficult>0</difficult>
		<bndbox>
			<xmin>2927</xmin>
			<ymin>2490</ymin>
			<xmax>4747</xmax>
			<ymax>2883</ymax>
		</bndbox>
	</object>
	<object>
		<name>208_Scope of deed_parties involved</name>
		<pose>Unspecified</pose>
		<truncated>0</truncated>
		<difficult>0</difficult>
		<bndbox>
			<xmin>2910</xmin>
			<ymin>2866</ymin>
			<xmax>4718</xmax>
			<ymax>3176</ymax>
		</bndbox>
	</object>
</annotation>